dalos/__init__.py
dalos-0.1.0a1.dist-info/METADATA
dalos-0.1.0a1.dist-info/RECORD
dalos-0.1.0a1.dist-info/WHEEL
dalos-0.1.0a1.dist-info/top_level.txt
