Metadata-Version: 2.1
Name: dalos
Version: 0.1.0a1
Summary: Implementations of common algorithms and data structures
Home-page: https://github.com/onelharrison/dalos
Author: Onel Harrison
Author-email: UNKNOWN
License: GNU General Public License v3
Platform: UNKNOWN
